{"config":{"output_file":null,"full_docs":false,"pub_only":true,"reachable_only":true,"distro_crate":false,"signatures":false,"borrow_data":false},"version":"0.19.0","compilation":{"directory":"/home/nullrequest/.cargo/registry/src/github.com-1ecc6299db9ec823/javascriptcore-rs-sys-0.2.0","program":"/home/nullrequest/.rustup/toolchains/nightly-x86_64-unknown-linux-gnu/bin/rls","arguments":["--crate-name","javascriptcore_sys","/home/nullrequest/.cargo/registry/src/github.com-1ecc6299db9ec823/javascriptcore-rs-sys-0.2.0/src/lib.rs","--json=diagnostic-rendered-ansi","--crate-type","lib","--emit=dep-info,metadata","-C","embed-bitcode=no","-C","debuginfo=2","-C","metadata=6aea5b388d6bffcf","-C","extra-filename=-6aea5b388d6bffcf","--out-dir","/home/nullrequest/egee-tools/distro-delves/custom_tools/custom_app/target/rls/debug/deps","-L","dependency=/home/nullrequest/egee-tools/distro-delves/custom_tools/custom_app/target/rls/debug/deps","--extern","libc=/home/nullrequest/egee-tools/distro-delves/custom_tools/custom_app/target/rls/debug/deps/liblibc-28c838524f3f8fde.rmeta","--cap-lints","allow","--error-format=json","--sysroot","/home/nullrequest/.rustup/toolchains/nightly-x86_64-unknown-linux-gnu"],"output":"/home/nullrequest/egee-tools/distro-delves/custom_tools/custom_app/target/rls/debug/deps/libjavascriptcore_sys-6aea5b388d6bffcf.rmeta"},"prelude":{"crate_id":{"name":"javascriptcore_sys","disambiguator":[16049337574819447496,5513209294513059470]},"crate_root":"/home/nullrequest/.cargo/registry/src/github.com-1ecc6299db9ec823/javascriptcore-rs-sys-0.2.0/src","external_crates":[{"file_name":"/home/nullrequest/.cargo/registry/src/github.com-1ecc6299db9ec823/javascriptcore-rs-sys-0.2.0/src/lib.rs","num":1,"id":{"name":"std","disambiguator":[5454670041059415339,14778898676712446032]}},{"file_name":"/home/nullrequest/.cargo/registry/src/github.com-1ecc6299db9ec823/javascriptcore-rs-sys-0.2.0/src/lib.rs","num":2,"id":{"name":"core","disambiguator":[6613225743082300914,1742833353142201501]}},{"file_name":"/home/nullrequest/.cargo/registry/src/github.com-1ecc6299db9ec823/javascriptcore-rs-sys-0.2.0/src/lib.rs","num":3,"id":{"name":"compiler_builtins","disambiguator":[11975364352078366518,17024437125936897165]}},{"file_name":"/home/nullrequest/.cargo/registry/src/github.com-1ecc6299db9ec823/javascriptcore-rs-sys-0.2.0/src/lib.rs","num":4,"id":{"name":"rustc_std_workspace_core","disambiguator":[7052056008796586215,10378193753915807487]}},{"file_name":"/home/nullrequest/.cargo/registry/src/github.com-1ecc6299db9ec823/javascriptcore-rs-sys-0.2.0/src/lib.rs","num":5,"id":{"name":"alloc","disambiguator":[7266508812970390764,1104721975748785438]}},{"file_name":"/home/nullrequest/.cargo/registry/src/github.com-1ecc6299db9ec823/javascriptcore-rs-sys-0.2.0/src/lib.rs","num":6,"id":{"name":"libc","disambiguator":[1008138081647881344,7429076406658465872]}},{"file_name":"/home/nullrequest/.cargo/registry/src/github.com-1ecc6299db9ec823/javascriptcore-rs-sys-0.2.0/src/lib.rs","num":7,"id":{"name":"unwind","disambiguator":[17323693314265278435,11165935492680790011]}},{"file_name":"/home/nullrequest/.cargo/registry/src/github.com-1ecc6299db9ec823/javascriptcore-rs-sys-0.2.0/src/lib.rs","num":8,"id":{"name":"cfg_if","disambiguator":[9336778117618987315,17870517156373193216]}},{"file_name":"/home/nullrequest/.cargo/registry/src/github.com-1ecc6299db9ec823/javascriptcore-rs-sys-0.2.0/src/lib.rs","num":9,"id":{"name":"hashbrown","disambiguator":[17103378408486634939,751433449546080727]}},{"file_name":"/home/nullrequest/.cargo/registry/src/github.com-1ecc6299db9ec823/javascriptcore-rs-sys-0.2.0/src/lib.rs","num":10,"id":{"name":"rustc_std_workspace_alloc","disambiguator":[10975069866030769009,5505173346458313804]}},{"file_name":"/home/nullrequest/.cargo/registry/src/github.com-1ecc6299db9ec823/javascriptcore-rs-sys-0.2.0/src/lib.rs","num":11,"id":{"name":"rustc_demangle","disambiguator":[6334346674486718091,8161957233453149106]}},{"file_name":"/home/nullrequest/.cargo/registry/src/github.com-1ecc6299db9ec823/javascriptcore-rs-sys-0.2.0/src/lib.rs","num":12,"id":{"name":"addr2line","disambiguator":[9975713641904480798,7580100659723909163]}},{"file_name":"/home/nullrequest/.cargo/registry/src/github.com-1ecc6299db9ec823/javascriptcore-rs-sys-0.2.0/src/lib.rs","num":13,"id":{"name":"gimli","disambiguator":[13017381940559774955,1473560800469322545]}},{"file_name":"/home/nullrequest/.cargo/registry/src/github.com-1ecc6299db9ec823/javascriptcore-rs-sys-0.2.0/src/lib.rs","num":14,"id":{"name":"object","disambiguator":[18046481696643307721,13304330266021309686]}},{"file_name":"/home/nullrequest/.cargo/registry/src/github.com-1ecc6299db9ec823/javascriptcore-rs-sys-0.2.0/src/lib.rs","num":15,"id":{"name":"miniz_oxide","disambiguator":[16808540700296544273,10362068119654760402]}},{"file_name":"/home/nullrequest/.cargo/registry/src/github.com-1ecc6299db9ec823/javascriptcore-rs-sys-0.2.0/src/lib.rs","num":16,"id":{"name":"adler","disambiguator":[10687136976133547149,15343372157523177244]}},{"file_name":"/home/nullrequest/.cargo/registry/src/github.com-1ecc6299db9ec823/javascriptcore-rs-sys-0.2.0/src/lib.rs","num":17,"id":{"name":"panic_unwind","disambiguator":[1758524798956620560,9236974138540026415]}},{"file_name":"/home/nullrequest/.cargo/registry/src/github.com-1ecc6299db9ec823/javascriptcore-rs-sys-0.2.0/src/lib.rs","num":18,"id":{"name":"libc","disambiguator":[12072356316885401511,8988549812514538938]}}],"span":{"file_name":"/home/nullrequest/.cargo/registry/src/github.com-1ecc6299db9ec823/javascriptcore-rs-sys-0.2.0/src/lib.rs","byte_start":227,"byte_end":1647,"line_start":5,"line_end":30,"column_start":1,"column_end":2}},"imports":[],"defs":[{"kind":"Mod","id":{"krate":0,"index":0},"span":{"file_name":"/home/nullrequest/.cargo/registry/src/github.com-1ecc6299db9ec823/javascriptcore-rs-sys-0.2.0/src/lib.rs","byte_start":227,"byte_end":1647,"line_start":5,"line_end":30,"column_start":1,"column_end":2},"name":"","qualname":"::","value":"/home/nullrequest/.cargo/registry/src/github.com-1ecc6299db9ec823/javascriptcore-rs-sys-0.2.0/src/lib.rs","parent":null,"children":[{"krate":0,"index":1},{"krate":0,"index":2},{"krate":0,"index":3},{"krate":0,"index":4},{"krate":0,"index":5},{"krate":0,"index":6},{"krate":0,"index":7},{"krate":0,"index":8},{"krate":0,"index":9},{"krate":0,"index":10},{"krate":0,"index":11},{"krate":0,"index":12},{"krate":0,"index":13}],"decl_id":null,"docs":"","sig":null,"attributes":[]},{"kind":"Type","id":{"krate":0,"index":8},"span":{"file_name":"/home/nullrequest/.cargo/registry/src/github.com-1ecc6299db9ec823/javascriptcore-rs-sys-0.2.0/src/lib.rs","byte_start":295,"byte_end":303,"line_start":9,"line_end":9,"column_start":10,"column_end":18},"name":"JSCValue","qualname":"::JSCValue","value":"*mut c_void","parent":null,"children":[],"decl_id":null,"docs":"","sig":null,"attributes":[]},{"kind":"Type","id":{"krate":0,"index":9},"span":{"file_name":"/home/nullrequest/.cargo/registry/src/github.com-1ecc6299db9ec823/javascriptcore-rs-sys-0.2.0/src/lib.rs","byte_start":328,"byte_end":338,"line_start":10,"line_end":10,"column_start":10,"column_end":20},"name":"JSCContext","qualname":"::JSCContext","value":"*mut c_void","parent":null,"children":[],"decl_id":null,"docs":"","sig":null,"attributes":[]},{"kind":"Type","id":{"krate":0,"index":10},"span":{"file_name":"/home/nullrequest/.cargo/registry/src/github.com-1ecc6299db9ec823/javascriptcore-rs-sys-0.2.0/src/lib.rs","byte_start":363,"byte_end":381,"line_start":11,"line_end":11,"column_start":10,"column_end":28},"name":"JSGlobalContextRef","qualname":"::JSGlobalContextRef","value":"*mut c_void","parent":null,"children":[],"decl_id":null,"docs":"","sig":null,"attributes":[]},{"kind":"Type","id":{"krate":0,"index":11},"span":{"file_name":"/home/nullrequest/.cargo/registry/src/github.com-1ecc6299db9ec823/javascriptcore-rs-sys-0.2.0/src/lib.rs","byte_start":406,"byte_end":416,"line_start":12,"line_end":12,"column_start":10,"column_end":20},"name":"JSValueRef","qualname":"::JSValueRef","value":"*mut c_void","parent":null,"children":[],"decl_id":null,"docs":"","sig":null,"attributes":[]},{"kind":"Type","id":{"krate":0,"index":12},"span":{"file_name":"/home/nullrequest/.cargo/registry/src/github.com-1ecc6299db9ec823/javascriptcore-rs-sys-0.2.0/src/lib.rs","byte_start":441,"byte_end":452,"line_start":13,"line_end":13,"column_start":10,"column_end":21},"name":"JSStringRef","qualname":"::JSStringRef","value":"*mut c_void","parent":null,"children":[],"decl_id":null,"docs":"","sig":null,"attributes":[]},{"kind":"ForeignFunction","id":{"krate":0,"index":14},"span":{"file_name":"/home/nullrequest/.cargo/registry/src/github.com-1ecc6299db9ec823/javascriptcore-rs-sys-0.2.0/src/lib.rs","byte_start":493,"byte_end":509,"line_start":16,"line_end":16,"column_start":12,"column_end":28},"name":"JSValueIsBoolean","qualname":"::JSValueIsBoolean","value":"pub unsafe extern \"C\" fn JSValueIsBoolean(ctx: JSGlobalContextRef,\n                                          value: JSValueRef) -> u8","parent":null,"children":[],"decl_id":null,"docs":"","sig":null,"attributes":[]},{"kind":"ForeignFunction","id":{"krate":0,"index":15},"span":{"file_name":"/home/nullrequest/.cargo/registry/src/github.com-1ecc6299db9ec823/javascriptcore-rs-sys-0.2.0/src/lib.rs","byte_start":572,"byte_end":585,"line_start":17,"line_end":17,"column_start":12,"column_end":25},"name":"JSValueIsNull","qualname":"::JSValueIsNull","value":"pub unsafe extern \"C\" fn JSValueIsNull(ctx: JSGlobalContextRef,\n                                       value: JSValueRef) -> u8","parent":null,"children":[],"decl_id":null,"docs":"","sig":null,"attributes":[]},{"kind":"ForeignFunction","id":{"krate":0,"index":16},"span":{"file_name":"/home/nullrequest/.cargo/registry/src/github.com-1ecc6299db9ec823/javascriptcore-rs-sys-0.2.0/src/lib.rs","byte_start":648,"byte_end":666,"line_start":18,"line_end":18,"column_start":12,"column_end":30},"name":"JSValueIsUndefined","qualname":"::JSValueIsUndefined","value":"pub unsafe extern \"C\" fn JSValueIsUndefined(ctx: JSGlobalContextRef,\n                                            value: JSValueRef) -> u8","parent":null,"children":[],"decl_id":null,"docs":"","sig":null,"attributes":[]},{"kind":"ForeignFunction","id":{"krate":0,"index":17},"span":{"file_name":"/home/nullrequest/.cargo/registry/src/github.com-1ecc6299db9ec823/javascriptcore-rs-sys-0.2.0/src/lib.rs","byte_start":729,"byte_end":744,"line_start":19,"line_end":19,"column_start":12,"column_end":27},"name":"JSValueIsNumber","qualname":"::JSValueIsNumber","value":"pub unsafe extern \"C\" fn JSValueIsNumber(ctx: JSGlobalContextRef,\n                                         value: JSValueRef) -> u8","parent":null,"children":[],"decl_id":null,"docs":"","sig":null,"attributes":[]},{"kind":"ForeignFunction","id":{"krate":0,"index":18},"span":{"file_name":"/home/nullrequest/.cargo/registry/src/github.com-1ecc6299db9ec823/javascriptcore-rs-sys-0.2.0/src/lib.rs","byte_start":807,"byte_end":822,"line_start":20,"line_end":20,"column_start":12,"column_end":27},"name":"JSValueIsString","qualname":"::JSValueIsString","value":"pub unsafe extern \"C\" fn JSValueIsString(ctx: JSGlobalContextRef,\n                                         value: JSValueRef) -> u8","parent":null,"children":[],"decl_id":null,"docs":"","sig":null,"attributes":[]},{"kind":"ForeignFunction","id":{"krate":0,"index":19},"span":{"file_name":"/home/nullrequest/.cargo/registry/src/github.com-1ecc6299db9ec823/javascriptcore-rs-sys-0.2.0/src/lib.rs","byte_start":885,"byte_end":900,"line_start":21,"line_end":21,"column_start":12,"column_end":27},"name":"JSValueIsObject","qualname":"::JSValueIsObject","value":"pub unsafe extern \"C\" fn JSValueIsObject(ctx: JSGlobalContextRef,\n                                         value: JSValueRef) -> u8","parent":null,"children":[],"decl_id":null,"docs":"","sig":null,"attributes":[]},{"kind":"ForeignFunction","id":{"krate":0,"index":20},"span":{"file_name":"/home/nullrequest/.cargo/registry/src/github.com-1ecc6299db9ec823/javascriptcore-rs-sys-0.2.0/src/lib.rs","byte_start":963,"byte_end":977,"line_start":22,"line_end":22,"column_start":12,"column_end":26},"name":"JSValueIsArray","qualname":"::JSValueIsArray","value":"pub unsafe extern \"C\" fn JSValueIsArray(ctx: JSGlobalContextRef,\n                                        value: JSValueRef) -> u8","parent":null,"children":[],"decl_id":null,"docs":"","sig":null,"attributes":[]},{"kind":"ForeignFunction","id":{"krate":0,"index":21},"span":{"file_name":"/home/nullrequest/.cargo/registry/src/github.com-1ecc6299db9ec823/javascriptcore-rs-sys-0.2.0/src/lib.rs","byte_start":1040,"byte_end":1053,"line_start":23,"line_end":23,"column_start":12,"column_end":25},"name":"JSValueIsDate","qualname":"::JSValueIsDate","value":"pub unsafe extern \"C\" fn JSValueIsDate(ctx: JSGlobalContextRef,\n                                       value: JSValueRef) -> u8","parent":null,"children":[],"decl_id":null,"docs":"","sig":null,"attributes":[]},{"kind":"ForeignFunction","id":{"krate":0,"index":22},"span":{"file_name":"/home/nullrequest/.cargo/registry/src/github.com-1ecc6299db9ec823/javascriptcore-rs-sys-0.2.0/src/lib.rs","byte_start":1116,"byte_end":1131,"line_start":24,"line_end":24,"column_start":12,"column_end":27},"name":"JSValueToNumber","qualname":"::JSValueToNumber","value":"pub unsafe extern \"C\" fn JSValueToNumber(ctx: JSGlobalContextRef,\n                                         value: JSValueRef,\n                                         exception: *mut JSValueRef)\n-> c_double","parent":null,"children":[],"decl_id":null,"docs":"","sig":null,"attributes":[]},{"kind":"ForeignFunction","id":{"krate":0,"index":23},"span":{"file_name":"/home/nullrequest/.cargo/registry/src/github.com-1ecc6299db9ec823/javascriptcore-rs-sys-0.2.0/src/lib.rs","byte_start":1228,"byte_end":1244,"line_start":25,"line_end":25,"column_start":12,"column_end":28},"name":"JSValueToBoolean","qualname":"::JSValueToBoolean","value":"pub unsafe extern \"C\" fn JSValueToBoolean(ctx: JSGlobalContextRef,\n                                          value: JSValueRef) -> u8","parent":null,"children":[],"decl_id":null,"docs":"","sig":null,"attributes":[]},{"kind":"ForeignFunction","id":{"krate":0,"index":24},"span":{"file_name":"/home/nullrequest/.cargo/registry/src/github.com-1ecc6299db9ec823/javascriptcore-rs-sys-0.2.0/src/lib.rs","byte_start":1307,"byte_end":1326,"line_start":26,"line_end":26,"column_start":12,"column_end":31},"name":"JSValueToStringCopy","qualname":"::JSValueToStringCopy","value":"pub unsafe extern \"C\" fn JSValueToStringCopy(ctx: JSGlobalContextRef,\n                                             value: JSValueRef,\n                                             exception: *mut JSValueRef)\n-> JSStringRef","parent":null,"children":[],"decl_id":null,"docs":"","sig":null,"attributes":[]},{"kind":"ForeignFunction","id":{"krate":0,"index":25},"span":{"file_name":"/home/nullrequest/.cargo/registry/src/github.com-1ecc6299db9ec823/javascriptcore-rs-sys-0.2.0/src/lib.rs","byte_start":1426,"byte_end":1441,"line_start":27,"line_end":27,"column_start":12,"column_end":27},"name":"JSStringRelease","qualname":"::JSStringRelease","value":"pub unsafe extern \"C\" fn JSStringRelease(string: JSStringRef)","parent":null,"children":[],"decl_id":null,"docs":"","sig":null,"attributes":[]},{"kind":"ForeignFunction","id":{"krate":0,"index":26},"span":{"file_name":"/home/nullrequest/.cargo/registry/src/github.com-1ecc6299db9ec823/javascriptcore-rs-sys-0.2.0/src/lib.rs","byte_start":1475,"byte_end":1508,"line_start":28,"line_end":28,"column_start":12,"column_end":45},"name":"JSStringGetMaximumUTF8CStringSize","qualname":"::JSStringGetMaximumUTF8CStringSize","value":"pub unsafe extern \"C\" fn JSStringGetMaximumUTF8CStringSize(string:\n                                                               JSStringRef)\n-> usize","parent":null,"children":[],"decl_id":null,"docs":"","sig":null,"attributes":[]},{"kind":"ForeignFunction","id":{"krate":0,"index":27},"span":{"file_name":"/home/nullrequest/.cargo/registry/src/github.com-1ecc6299db9ec823/javascriptcore-rs-sys-0.2.0/src/lib.rs","byte_start":1551,"byte_end":1573,"line_start":29,"line_end":29,"column_start":12,"column_end":34},"name":"JSStringGetUTF8CString","qualname":"::JSStringGetUTF8CString","value":"pub unsafe extern \"C\" fn JSStringGetUTF8CString(string: JSStringRef,\n                                                buffer: *mut c_char,\n                                                buffer_size: usize) -> usize","parent":null,"children":[],"decl_id":null,"docs":"","sig":null,"attributes":[]}],"impls":[],"refs":[],"macro_refs":[],"relations":[]}